CodEasy/__init__.py
CodEasy/conditionals.py
CodEasy/file_ops.py
CodEasy/loops.py
CodEasy-0.1.dist-info/LICENSE
CodEasy-0.1.dist-info/METADATA
CodEasy-0.1.dist-info/WHEEL
CodEasy-0.1.dist-info/top_level.txt
CodEasy-0.1.dist-info/RECORD
